ng_nx/__init__.py
ng_nx/query_reader.py
ng_nx/scan_reader.py
ng_nx/utils.py
ng_nx/writer.py
ng_nx-0.2.3.dist-info/WHEEL
ng_nx-0.2.3.dist-info/METADATA
ng_nx-0.2.3.dist-info/licenses/LICENSE
ng_nx-0.2.3.dist-info/RECORD
