Metadata-Version: 2.1
Name: ng_nx
Version: 0.2.3
Summary: NebulaGraph NetowrkX Adaptor
License: Apache-2.0
Author-email: Wey Gu <weyl.gu@gmail.com>
Requires-Python: >=3.7.1
Classifier: License :: OSI Approved :: Apache Software License
Classifier: Operating System :: OS Independent
Classifier: Programming Language :: Python :: 3
Classifier: Programming Language :: Python :: 3.10
Classifier: Programming Language :: Python :: 3.7
Classifier: Programming Language :: Python :: 3.8
Classifier: Programming Language :: Python :: 3.9
Classifier: Topic :: Software Development :: Build Tools
Requires-Dist: nebula3-python>=3.8.2
Requires-Dist: networkx>=2.5.1
Provides-Extra: dev
Requires-Dist: ng_nx[lint,test]; extra == "dev"
Provides-Extra: lint
Requires-Dist: flake8>=4.0.1; extra == "lint"
Requires-Dist: black[jupyter]>=23.1.0; extra == "lint"
Requires-Dist: isort>=5.11.5; extra == "lint"
Provides-Extra: test
Requires-Dist: pytest>=7.2.2; extra == "test"
Requires-Dist: pytest-mock>=3.10.0; extra == "test"
Project-URL: Changelog, https://github.com/wey-gu/nebulagraph-nx/releases
Project-URL: Documentation, https://github.com/wey-gu/nebulagraph-nx#documentation
Project-URL: Homepage, https://github.com/wey-gu/nebulagraph-nx
Project-URL: Repository, https://github.com/wey-gu/nebulagraph-nx
